pytibber-0.35.0.dist-info/licenses/LICENSE
tibber/__init__.py
tibber/const.py
tibber/data_api.py
tibber/exceptions.py
tibber/gql_queries.py
tibber/home.py
tibber/py.typed
tibber/realtime.py
tibber/response_handler.py
tibber/websocket_transport.py
pytibber-0.35.0.dist-info/METADATA
pytibber-0.35.0.dist-info/WHEEL
pytibber-0.35.0.dist-info/top_level.txt
pytibber-0.35.0.dist-info/RECORD
