Metadata-Version: 2.4
Name: pyTibber
Version: 0.35.0
Summary: A python3 library to communicate with Tibber
Author-email: Daniel Hjelseth Hoyer <mail@dahoiv.net>
License-Expression: GPL-3.0-or-later
Project-URL: Source code, https://github.com/Danielhiversen/pyTibber
Classifier: Intended Audience :: Developers
Classifier: Operating System :: OS Independent
Classifier: Programming Language :: Python
Classifier: Programming Language :: Python :: 3
Classifier: Topic :: Home Automation
Classifier: Topic :: Software Development :: Libraries :: Python Modules
Requires-Python: >=3.11
License-File: LICENSE
Requires-Dist: aiohttp>=3.0.6
Requires-Dist: gql==3.5.0
Requires-Dist: websockets>=14.0.0
Dynamic: license-file
